{"cameraMode":{"drawMode":0,"name":"Shaded","section":"Shading Mode"},"sceneLighting":false,"audioPlay":false,"sceneViewState":{"showFog":false,"showMaterialUpdate":false,"showSkybox":false,"showFlares":false,"showImageEffects":false,"showParticleSystems":false},"in2DMode":false,"pivot":{"x":0.4837411344051361,"y":0.5,"z":5.960464477539063e-8},"rotation":{"x":-0.10264062881469727,"y":-0.8309419751167297,"z":0.1624218374490738,"w":-0.5235093235969544},"size":2.3347115516662599,"orthographic":false}