{"cameraMode":{"drawMode":0,"name":"Shaded","section":"Shading Mode"},"sceneLighting":false,"audioPlay":false,"sceneViewState":{"showFog":true,"showMaterialUpdate":false,"showSkybox":false,"showFlares":true,"showImageEffects":true,"showParticleSystems":true},"in2DMode":false,"pivot":{"x":0.0004141479730606079,"y":0.2344922125339508,"z":-1.8745620250701905},"rotation":{"x":-0.2175271064043045,"y":0.2325141280889511,"z":-0.05345633253455162,"w":-0.9464746117591858},"size":0.797977864742279,"orthographic":false}